beancount_ast/__init__.py
beancount_ast/_ast.abi3.so
beancount_ast/_ast.pyi
beancount_ast/_directive.py
beancount_ast/py.typed
beancount_ast-0.0.1a3.dist-info/METADATA
beancount_ast-0.0.1a3.dist-info/WHEEL
beancount_ast-0.0.1a3.dist-info/RECORD
