Metadata-Version: 2.4
Name: beancount_ast
Version: 0.0.1a3
Summary: Parse Beancount content into AST
Home-Page: https://github.com/trim21/beancount-ast
Requires-Python: >=3.10
